rest_enumfield/__init__.py
rest_enumfield/__version__.py
rest_enumfield/fields.py
django_rest_enumfield-0.2.0.dist-info/LICENSE
django_rest_enumfield-0.2.0.dist-info/METADATA
django_rest_enumfield-0.2.0.dist-info/WHEEL
django_rest_enumfield-0.2.0.dist-info/top_level.txt
django_rest_enumfield-0.2.0.dist-info/RECORD
